beegen/__init__.py
beegen/__main__.py
beegen/__version__.py
beegen/application.py
beegen/commands/__init__.py
beegen/commands/about.py
beegen/commands/base.py
beegen/commands/configure.py
beegen/commands/mock/__init__.py
beegen/commands/mock/create.py
beegen/commands/mock/run.py
beegen/commands/mock/schema.json
beegen/commands/smart/__init__.py
beegen/commands/smart/anonymize_data.py
beegen/commands/smart/base.py
beegen/commands/smart/core/__init__.py
beegen/commands/smart/core/chain.py
beegen/commands/smart/core/provider.py
beegen/commands/smart/core/vector_store.py
beegen/commands/smart/pull_request_desc.py
beegen/commands/smart/readme.py
beegen/commands/smart/regex.py
beegen/commands/smart/translate.py
beegen/commands/smart/vector_store.py
beegen/commands/snippets/__init__.py
beegen/commands/snippets/add.py
beegen/commands/snippets/base.py
beegen/commands/snippets/list.py
beegen/commands/snippets/remove.py
beegen/commands/snippets/use.py
beegen/commands/utils/__init__.py
beegen/commands/utils/chat.py
beegen/config/__init__.py
beegen/config/settings.py
beegen/services/__init__.py
beegen/services/chat/__init__.py
beegen/services/chat/app.py
beegen/services/chat/components/__init__.py
beegen/services/chat/components/images/beegen.png
beegen/services/chat/components/images/favicon.ico
beegen/services/chat/components/page_config.py
beegen/services/chat/pages/__init__.py
beegen/services/chat/pages/playground.py
beegen/services/chat/pages/settings.py
beegen/services/mock.py
beegen-0.1.5.dist-info/LICENSE
beegen-0.1.5.dist-info/METADATA
beegen-0.1.5.dist-info/WHEEL
beegen-0.1.5.dist-info/entry_points.txt
beegen-0.1.5.dist-info/RECORD
