Metadata-Version: 2.1
Name: beegen
Version: 0.1.5
Summary: BeeGen is an intelligent command-line tool designed to assist developers with everyday tasks, leveraging the power of generative AI.
Home-page: https://github.com/pavanad/beegen
License: MIT
Author: Adilson Pavan
Author-email: adilson.pavan@gmail.com
Requires-Python: >=3.10,<4.0
Classifier: License :: OSI Approved :: MIT License
Classifier: Programming Language :: Python :: 3
Classifier: Programming Language :: Python :: 3.10
Classifier: Programming Language :: Python :: 3.11
Classifier: Programming Language :: Python :: 3.12
Classifier: Programming Language :: Python :: 3.13
Requires-Dist: cleo (>=2.1.0,<3.0.0)
Requires-Dist: faiss-cpu (>=1.8.0,<2.0.0)
Requires-Dist: fastapi (>=0.111.0,<0.112.0)
Requires-Dist: gitpython (>=3.1.43,<4.0.0)
Requires-Dist: jsonschema (>=4.22.0,<5.0.0)
Requires-Dist: langchain (>=0.2.1,<0.3.0)
Requires-Dist: langchain-community (>=0.2.1,<0.3.0)
Requires-Dist: langchain-google-genai (>=1.0.5,<2.0.0)
Requires-Dist: langchain-openai (>=0.1.8,<0.2.0)
Requires-Dist: pyfiglet (>=1.0.2,<2.0.0)
Requires-Dist: pypdf (>=4.2.0,<5.0.0)
Requires-Dist: rich (>=13.7.1,<14.0.0)
Requires-Dist: streamlit (>=1.35.0,<2.0.0)
Requires-Dist: streamlit-ace (>=0.1.1,<0.2.0)
Requires-Dist: tqdm (>=4.66.4,<5.0.0)
Requires-Dist: uvicorn (>=0.29.0,<0.30.0)
Project-URL: Repository, https://github.com/pavanad/beegen
